echome_cli/__init__.py
echome_cli/base_service.py
echome_cli/defaults.py
echome_cli/identity.py
echome_cli/keys.py
echome_cli/kube.py
echome_cli/main.py
echome_cli/network.py
echome_cli/vm.py
echome_cli-0.3.2.dist-info/LICENSE
echome_cli-0.3.2.dist-info/METADATA
echome_cli-0.3.2.dist-info/WHEEL
echome_cli-0.3.2.dist-info/entry_points.txt
echome_cli-0.3.2.dist-info/top_level.txt
echome_cli-0.3.2.dist-info/RECORD
