Metadata-Version: 2.1
Name: echome-cli
Version: 0.3.2
Summary: EcHome CLI
Home-page: https://github.com/mgtrrz/echome-cli
Author: Marcus Gutierrez
Author-email: markg90@gmail.com
License: UNKNOWN
Platform: UNKNOWN
Classifier: Programming Language :: Python :: 3
Classifier: License :: OSI Approved :: MIT License
Classifier: Operating System :: OS Independent
Requires-Python: >=3.6
License-File: LICENSE
Requires-Dist: echome-sdk (==0.5.1)
Requires-Dist: requests (>=2.24)
Requires-Dist: tabulate (>=0.8.7)
